Metadata-Version: 2.1
Name: model-selector
Version: 1.0.1
Summary: This package will help you select the regression model or classification model for your dataset. Provide the file path to your dataset and watch this package do the rest of the work for you.
Home-page: https://github.com/halculvin/model_selector
Author: Harry McNinson
Author-email: harrymn@uw.edu
License: UNKNOWN
Platform: UNKNOWN
Classifier: Programming Language :: Python :: 3
Classifier: License :: OSI Approved :: MIT License
Classifier: Operating System :: OS Independent
License-File: LICENSE.txt
